browsertotal_scanner/__init__.py
browsertotal_scanner/py.typed
browsertotal_scanner/scanner.py
browsertotal_scanner/types.py
browsertotal_scanner-1.0.1.dist-info/METADATA
browsertotal_scanner-1.0.1.dist-info/WHEEL
browsertotal_scanner-1.0.1.dist-info/licenses/LICENSE
browsertotal_scanner-1.0.1.dist-info/RECORD
