Metadata-Version: 2.4
Name: browsertotal-scanner
Version: 1.0.1
Summary: Security scanner for URLs, browser extensions, IDE plugins, and software packages using BrowserTotal
Project-URL: Homepage, https://browsertotal.com
Project-URL: Documentation, https://github.com/SeraphicSecurity/BrowserTotal
Project-URL: Repository, https://github.com/SeraphicSecurity/BrowserTotal
Project-URL: Issues, https://github.com/SeraphicSecurity/BrowserTotal/issues
Author-email: BrowserTotal <support@browsertotal.com>
License-Expression: MIT
License-File: LICENSE
Keywords: browser,browsertotal,chrome,extension,firefox,malware,npm,pypi,scanner,security,url,vscode
Classifier: Development Status :: 4 - Beta
Classifier: Intended Audience :: Developers
Classifier: License :: OSI Approved :: MIT License
Classifier: Operating System :: OS Independent
Classifier: Programming Language :: Python :: 3
Classifier: Programming Language :: Python :: 3.9
Classifier: Programming Language :: Python :: 3.10
Classifier: Programming Language :: Python :: 3.11
Classifier: Programming Language :: Python :: 3.12
Classifier: Programming Language :: Python :: 3.13
Classifier: Topic :: Security
Classifier: Topic :: Software Development :: Libraries :: Python Modules
Classifier: Typing :: Typed
Requires-Python: >=3.9
Requires-Dist: httpx>=0.24.0
Requires-Dist: playwright>=1.40.0
Provides-Extra: dev
Requires-Dist: mypy>=1.0.0; extra == 'dev'
Requires-Dist: pytest-asyncio>=0.21.0; extra == 'dev'
Requires-Dist: pytest>=7.0.0; extra == 'dev'
Requires-Dist: ruff>=0.1.0; extra == 'dev'
